aipython/__init__.py
aipython/__main__.py
aipython/base.py
async_ipython-0.0.4.dist-info/entry_points.txt
async_ipython-0.0.4.dist-info/LICENSE
async_ipython-0.0.4.dist-info/WHEEL
async_ipython-0.0.4.dist-info/METADATA
async_ipython-0.0.4.dist-info/RECORD
